{
  "meridian": "Pericardium",
  "element": "fire",
  "view": "front",
  "points": [
    {
      "id": "PC1",
      "name": "Chuhn Jee",
      "meridian": "Pericardium",
      "description": "Heaven's Pool",
      "region": "Trunk Front",
      "x": 0.4098,
      "y": 0.2893
    },
    {
      "id": "PC2",
      "name": "Chuhn Chuhn",
      "meridian": "Pericardium",
      "description": "Heaven's Spring",
      "region": "Arms Front",
      "x": 0.3117,
      "y": 0.2868
    },
    {
      "id": "PC3",
      "name": "Gohk Taek",
      "meridian": "Pericardium",
      "description": "Curved Marsh",
      "region": "Arms Front",
      "x": 0.2886,
      "y": 0.3798
    },
    {
      "id": "PC4",
      "name": "Geuk Moon",
      "meridian": "Pericardium",
      "description": "Cleft Gate",
      "region": "Arms Front",
      "x": 0.2395,
      "y": 0.4354
    },
    {
      "id": "PC5",
      "name": "Kahn Sah",
      "meridian": "Pericardium",
      "description": "Intermediary Messenger",
      "region": "Arms Front",
      "x": 0.2294,
      "y": 0.4565
    },
    {
      "id": "PC6",
      "name": "Nae Gwahn",
      "meridian": "Pericardium",
      "description": "Inner Pass",
      "region": "Arms Front",
      "x": 0.2222,
      "y": 0.468
    },
    {
      "id": "PC7",
      "name": "Tae Neung",
      "meridian": "Pericardium",
      "description": "Great Mound",
      "region": "Arms Front",
      "x": 0.2136,
      "y": 0.4801
    },
    {
      "id": "PC8",
      "name": "Noh Goong",
      "meridian": "Pericardium",
      "description": "Labor Palace",
      "region": "Arms Front",
      "x": 0.1789,
      "y": 0.5109
    },
    {
      "id": "PC9",
      "name": "Joong Choong",
      "meridian": "Pericardium",
      "description": "Central Rush",
      "region": "Arms Front",
      "x": 0.1732,
      "y": 0.567
    }
  ]
}
